dict2sql/__init__.py
dict2sql/compiler_misc.py
dict2sql/dialects/__init__.py
dict2sql/dialects/ansi/__init__.py
dict2sql/dialects/ansi/clause_from.py
dict2sql/dialects/ansi/clause_limit.py
dict2sql/dialects/ansi/clause_select.py
dict2sql/dialects/ansi/clause_where.py
dict2sql/dialects/ansi/sqlite_test.py
dict2sql/dialects/ansi/statement.py
dict2sql/dialects/ansi/statement_delete.py
dict2sql/dialects/ansi/statement_insert.py
dict2sql/dialects/ansi/statement_select.py
dict2sql/dialects/ansi/statement_update.py
dict2sql/dialects/ansi/utils.py
dict2sql/test_fixtures/chinhook.sqlite3
dict2sql/test_fixtures/utils.py
dict2sql/types.py
dict2sql/utils.py
dict2sql-2.1.0.dist-info/LICENSE
dict2sql-2.1.0.dist-info/WHEEL
dict2sql-2.1.0.dist-info/METADATA
dict2sql-2.1.0.dist-info/RECORD
