Metadata-Version: 2.1
Name: dict2sql
Version: 2.1.0
Summary: 
Home-page: https://github.com/simonacca/dict2sql
License: MIT
Author: Simon Accascina
Author-email: simon@accascina.me
Requires-Python: >=3.6,<4.0
Classifier: License :: OSI Approved :: MIT License
Classifier: Programming Language :: Python :: 3
Classifier: Programming Language :: Python :: 3.6
Classifier: Programming Language :: Python :: 3.7
Classifier: Programming Language :: Python :: 3.8
Classifier: Programming Language :: Python :: 3.9
Requires-Dist: SQLAlchemy (>=1.4.13,<2.0.0)
Requires-Dist: toolz (>=0.11.1,<0.12.0)
Requires-Dist: typing-extensions (>=3.10.0,<4.0.0)
Project-URL: Repository, https://github.com/simonacca/dict2sql
